{
    "Table": {
        "AttributeDefinitions": [
            {
                "AttributeName": "problemId",
                "AttributeType": "N"
            },
            {
                "AttributeName": "userId",
                "AttributeType": "S"
            }
        ],
        "TableName": "learnjs",
        "KeySchema": [
            {
                "AttributeName": "userId",
                "KeyType": "HASH"
            },
            {
                "AttributeName": "problemId",
                "KeyType": "RANGE"
            }
        ],
        "TableStatus": "ACTIVE",
        "CreationDateTime": 1558095394.832,
        "ProvisionedThroughput": {
            "NumberOfDecreasesToday": 0,
            "ReadCapacityUnits": 5,
            "WriteCapacityUnits": 5
        },
        "TableSizeBytes": 0,
        "ItemCount": 0,
        "TableArn": "arn:aws:dynamodb:us-east-1:391249486863:table/learnjs",
        "TableId": "0098e83e-2db7-47be-829a-da9505ad165d"
    }
}
